claude2openai/__init__.py
claude2openai/__main__.py
claude2openai/main.py
claude2openai/sse.py
claude_openai_bridge-0.1.0.dist-info/licenses/LICENSE
claude_openai_bridge-0.1.0.dist-info/METADATA
claude_openai_bridge-0.1.0.dist-info/WHEEL
claude_openai_bridge-0.1.0.dist-info/entry_points.txt
claude_openai_bridge-0.1.0.dist-info/top_level.txt
claude_openai_bridge-0.1.0.dist-info/RECORD
